illuminat/CENTAUR.TTF
illuminat/CENTAURreg.TTF
illuminat/Cell.png
illuminat/Cow.png
illuminat/Cow.png_1.png
illuminat/English1102SEC1.txt
illuminat/English1301FUL1.txt
illuminat/English1301MAT1.txt
illuminat/English1302NET1.txt
illuminat/English1302SEC1.txt
illuminat/English1303CLI1.txt
illuminat/English1303PPL1.txt
illuminat/English13101FUL1.txt
illuminat/English13101MAT1.txt
illuminat/English13101TIS1.txt
illuminat/English13102NET1.txt
illuminat/English13102OFF1.txt
illuminat/English13102SEC1.txt
illuminat/English13103CLI1.txt
illuminat/English13103NAT1.txt
illuminat/English13103PPL1.txt
illuminat/English13103WOR1.txt
illuminat/English1311FUL1.txt
illuminat/English1311MAT1.txt
illuminat/English1312NET1.txt
illuminat/English1312SEC1.txt
illuminat/English1313CLI1.txt
illuminat/English1313PPL1.txt
illuminat/English1321FUL1.txt
illuminat/English1321MAT1.txt
illuminat/English1322NET1.txt
illuminat/English1322SEC1.txt
illuminat/English1323CLI1.txt
illuminat/English1323PPL1.txt
illuminat/English132COR1.txt
illuminat/English1331FUL1.txt
illuminat/English1331MAT1.txt
illuminat/English1332NET1.txt
illuminat/English1332SEC1.txt
illuminat/English1333CLI1.txt
illuminat/English1333PPL1.txt
illuminat/English1341FUL1.txt
illuminat/English1341MAT1.txt
illuminat/English1341TIS1.txt
illuminat/English1342NET1.txt
illuminat/English1342OFF1.txt
illuminat/English1342SEC1.txt
illuminat/English1343CLI1.txt
illuminat/English1343PPL1.txt
illuminat/English1343WOR1.txt
illuminat/English1351FUL1.txt
illuminat/English1351MAT1.txt
illuminat/English1351TIS1.txt
illuminat/English1352NET1.txt
illuminat/English1352OFF1.txt
illuminat/English1352SEC1.txt
illuminat/English1353CLI1.txt
illuminat/English1353PPL1.txt
illuminat/English1353WOR1.txt
illuminat/English1361FUL1.txt
illuminat/English1361FUL1.wav
illuminat/English1361MAT1.txt
illuminat/English1361TIS1.txt
illuminat/English1362NET1.txt
illuminat/English1362OFF1.txt
illuminat/English1362SEC1.txt
illuminat/English1363CLI1.txt
illuminat-1.4.1.dist-info/METADATA
illuminat-1.4.1.dist-info/WHEEL
illuminat-1.4.1.dist-info/top_level.txt
illuminat-1.4.1.dist-info/RECORD
