Metadata-Version: 2.1
Name: illuminat
Version: 1.4.1
Summary: Illuminat: Revolutionizing Education through Personalization
Author: Amey Aggarwal
Author-email: <ameyaggarwal.sms@gmail.com>
Keywords: python,video,stream,video stream,camera stream,sockets
Classifier: Development Status :: 1 - Planning
Classifier: Intended Audience :: Developers
Classifier: Programming Language :: Python :: 3
Classifier: Operating System :: Unix
Classifier: Operating System :: MacOS :: MacOS X
Classifier: Operating System :: Microsoft :: Windows
Requires-Dist: adal (==1.2.7)
Requires-Dist: aiohttp (==3.9.3)
Requires-Dist: aiosignal (==1.3.1)
Requires-Dist: altgraph (==0.17.4)
Requires-Dist: annotated-types (==0.6.0)
Requires-Dist: anyio (==4.2.0)
Requires-Dist: appdirs (==1.4.4)
Requires-Dist: asyncgui (==0.6.1)
Requires-Dist: asyncio (==3.4.3)
Requires-Dist: asynckivy (==0.6.2)
Requires-Dist: attrs (==23.2.0)
Requires-Dist: audioread (==3.0.1)
Requires-Dist: auto-py-to-exe (==2.43.3)
Requires-Dist: azure-ai-textanalytics (==5.3.0)
Requires-Dist: azure-ai-translation-text (==1.0.0b1)
Requires-Dist: azure-applicationinsights (==0.1.1)
Requires-Dist: azure-batch (==4.1.3)
Requires-Dist: azure-cognitiveservices-language-luis (==0.7.0)
Requires-Dist: azure-cognitiveservices-language-spellcheck (==2.0.0)
Requires-Dist: azure-cognitiveservices-language-textanalytics (==0.2.1)
Requires-Dist: azure-cognitiveservices-speech (==1.36.0)
Requires-Dist: azure-common (==1.1.28)
Requires-Dist: azure-core (==1.30.1)
Requires-Dist: azure-cosmosdb-nspkg (==2.0.2)
Requires-Dist: azure-cosmosdb-table (==1.0.6)
Requires-Dist: azure-datalake-store (==0.0.53)
Requires-Dist: azure-eventgrid (==1.3.0)
Requires-Dist: azure-graphrbac (==0.40.0)
Requires-Dist: azure-identity (==1.15.0)
Requires-Dist: azure-keyvault (==1.1.0)
Requires-Dist: azure-loganalytics (==0.1.1)
Requires-Dist: azure-mgmt (==4.0.0)
Requires-Dist: azure-mgmt-advisor (==1.0.1)
Requires-Dist: azure-mgmt-applicationinsights (==0.1.1)
Requires-Dist: azure-mgmt-authorization (==0.50.0)
Requires-Dist: azure-mgmt-batch (==5.0.1)
Requires-Dist: azure-mgmt-batchai (==2.0.0)
Requires-Dist: azure-mgmt-billing (==0.2.0)
Requires-Dist: azure-mgmt-cdn (==3.1.0)
Requires-Dist: azure-mgmt-cognitiveservices (==3.0.0)
Requires-Dist: azure-mgmt-commerce (==1.0.1)
Requires-Dist: azure-mgmt-compute (==4.6.2)
Requires-Dist: azure-mgmt-consumption (==2.0.0)
Requires-Dist: azure-mgmt-containerinstance (==1.5.0)
Requires-Dist: azure-mgmt-containerregistry (==2.8.0)
Requires-Dist: azure-mgmt-containerservice (==4.4.0)
Requires-Dist: azure-mgmt-core (==1.4.0)
Requires-Dist: azure-mgmt-cosmosdb (==0.4.1)
Requires-Dist: azure-mgmt-datafactory (==0.6.0)
Requires-Dist: azure-mgmt-datalake-analytics (==0.6.0)
Requires-Dist: azure-mgmt-datalake-nspkg (==3.0.1)
Requires-Dist: azure-mgmt-datalake-store (==0.5.0)
Requires-Dist: azure-mgmt-datamigration (==1.0.0)
Requires-Dist: azure-mgmt-devspaces (==0.1.0)
Requires-Dist: azure-mgmt-devtestlabs (==2.2.0)
Requires-Dist: azure-mgmt-dns (==2.1.0)
Requires-Dist: azure-mgmt-eventgrid (==1.0.0)
Requires-Dist: azure-mgmt-eventhub (==2.6.0)
Requires-Dist: azure-mgmt-hanaonazure (==0.1.1)
Requires-Dist: azure-mgmt-iotcentral (==0.1.0)
Requires-Dist: azure-mgmt-iothub (==0.5.0)
Requires-Dist: azure-mgmt-iothubprovisioningservices (==0.2.0)
Requires-Dist: azure-mgmt-keyvault (==1.1.0)
Requires-Dist: azure-mgmt-loganalytics (==0.2.0)
Requires-Dist: azure-mgmt-logic (==3.0.0)
Requires-Dist: azure-mgmt-machinelearningcompute (==0.4.1)
Requires-Dist: azure-mgmt-managementgroups (==0.1.0)
Requires-Dist: azure-mgmt-managementpartner (==0.1.1)
Requires-Dist: azure-mgmt-maps (==0.1.0)
Requires-Dist: azure-mgmt-marketplaceordering (==0.1.0)
Requires-Dist: azure-mgmt-media (==1.0.1)
Requires-Dist: azure-mgmt-monitor (==0.5.2)
Requires-Dist: azure-mgmt-msi (==0.2.0)
Requires-Dist: azure-mgmt-network (==2.7.0)
Requires-Dist: azure-mgmt-notificationhubs (==2.1.0)
Requires-Dist: azure-mgmt-nspkg (==3.0.2)
Requires-Dist: azure-mgmt-policyinsights (==0.1.0)
Requires-Dist: azure-mgmt-powerbiembedded (==2.0.0)
Requires-Dist: azure-mgmt-rdbms (==1.9.0)
Requires-Dist: azure-mgmt-recoveryservices (==0.3.0)
Requires-Dist: azure-mgmt-recoveryservicesbackup (==0.3.0)
Requires-Dist: azure-mgmt-redis (==5.0.0)
Requires-Dist: azure-mgmt-relay (==0.1.0)
Requires-Dist: azure-mgmt-reservations (==0.2.1)
Requires-Dist: azure-mgmt-resource (==2.2.0)
Requires-Dist: azure-mgmt-scheduler (==2.0.0)
Requires-Dist: azure-mgmt-search (==2.1.0)
Requires-Dist: azure-mgmt-servicebus (==0.5.3)
Requires-Dist: azure-mgmt-servicefabric (==0.2.0)
Requires-Dist: azure-mgmt-signalr (==0.1.1)
Requires-Dist: azure-mgmt-sql (==0.9.1)
Requires-Dist: azure-mgmt-storage (==2.0.0)
Requires-Dist: azure-mgmt-subscription (==0.2.0)
Requires-Dist: azure-mgmt-trafficmanager (==0.50.0)
Requires-Dist: azure-mgmt-web (==0.35.0)
Requires-Dist: azure-nspkg (==3.0.2)
Requires-Dist: azure-servicebus (==0.21.1)
Requires-Dist: azure-servicefabric (==6.3.0.0)
Requires-Dist: azure-servicemanagement-legacy (==0.20.7)
Requires-Dist: azure-storage-blob (==1.5.0)
Requires-Dist: azure-storage-common (==1.4.2)
Requires-Dist: azure-storage-file (==1.4.0)
Requires-Dist: azure-storage-queue (==1.4.0)
Requires-Dist: backports.tarfile (==1.0.0)
Requires-Dist: blinker (==1.7.0)
Requires-Dist: bottle (==0.12.25)
Requires-Dist: bottle-websocket (==0.2.9)
Requires-Dist: build (==1.0.3)
Requires-Dist: buildozer (==1.5.0)
Requires-Dist: CacheControl (==0.13.1)
Requires-Dist: cachetools (==5.3.2)
Requires-Dist: certifi (==2024.2.2)
Requires-Dist: cffi (==1.16.0)
Requires-Dist: chardet (==3.0.4)
Requires-Dist: charset-normalizer (==3.3.2)
Requires-Dist: click (==8.1.7)
Requires-Dist: colorama (==0.4.6)
Requires-Dist: cryptography (==41.0.7)
Requires-Dist: Cython (==0.29.19)
Requires-Dist: decorator (==4.4.2)
Requires-Dist: distlib (==0.3.8)
Requires-Dist: distro (==1.9.0)
Requires-Dist: docutils (==0.20.1)
Requires-Dist: Eel (==0.16.0)
Requires-Dist: et-xmlfile (==1.1.0)
Requires-Dist: ffpyplayer (==4.5.1)
Requires-Dist: filelock (==3.13.1)
Requires-Dist: firebase-admin (==6.4.0)
Requires-Dist: Flask (==3.0.2)
Requires-Dist: frozenlist (==1.4.1)
Requires-Dist: fsspec (==2024.3.1)
Requires-Dist: future (==1.0.0)
Requires-Dist: gevent (==24.2.1)
Requires-Dist: gevent-websocket (==0.10.1)
Requires-Dist: google-api-core (==2.15.0)
Requires-Dist: google-api-python-client (==2.113.0)
Requires-Dist: google-auth (==2.29.0)
Requires-Dist: google-auth-httplib2 (==0.2.0)
Requires-Dist: google-cloud-core (==2.4.1)
Requires-Dist: google-cloud-firestore (==2.14.0)
Requires-Dist: google-cloud-storage (==2.14.0)
Requires-Dist: google-crc32c (==1.5.0)
Requires-Dist: google-resumable-media (==2.7.0)
Requires-Dist: googleapis-common-protos (==1.62.0)
Requires-Dist: greenlet (==3.0.3)
Requires-Dist: grpcio (==1.60.0)
Requires-Dist: grpcio-status (==1.60.0)
Requires-Dist: gTTS (==2.5.1)
Requires-Dist: h11 (==0.14.0)
Requires-Dist: h2 (==3.2.0)
Requires-Dist: hpack (==3.0.0)
Requires-Dist: hstspreload (==2024.2.1)
Requires-Dist: httpcore (==1.0.4)
Requires-Dist: httplib2 (==0.22.0)
Requires-Dist: httpx (==0.27.0)
Requires-Dist: huggingface-hub (==0.22.2)
Requires-Dist: hyperframe (==5.2.0)
Requires-Dist: idna (==3.6)
Requires-Dist: imageio (==2.33.1)
Requires-Dist: imageio-ffmpeg (==0.4.9)
Requires-Dist: importlib-metadata (==7.1.0)
Requires-Dist: isodate (==0.6.1)
Requires-Dist: itsdangerous (==2.1.2)
Requires-Dist: jaraco.classes (==3.4.0)
Requires-Dist: jaraco.context (==5.3.0)
Requires-Dist: jaraco.functools (==4.0.0)
Requires-Dist: Jinja2 (==3.1.3)
Requires-Dist: joblib (==1.3.2)
Requires-Dist: keyring (==25.1.0)
Requires-Dist: kivy
Requires-Dist: kivy-deps.angle (==0.4.0)
Requires-Dist: kivy-deps.glew (==0.3.1)
Requires-Dist: kivy-deps.sdl2 (==0.7.0)
Requires-Dist: Kivy-Garden (==0.1.5)
Requires-Dist: kivymd (==1.2.0)
Requires-Dist: lazy-loader (==0.3)
Requires-Dist: libretranslatepy (==2.1.1)
Requires-Dist: librosa (==0.10.1)
Requires-Dist: llvmlite (==0.42.0)
Requires-Dist: lxml (==5.1.0)
Requires-Dist: markdown-it-py (==3.0.0)
Requires-Dist: MarkupSafe (==2.1.5)
Requires-Dist: materialyoucolor (==2.0.7)
Requires-Dist: mdurl (==0.1.2)
Requires-Dist: more-itertools (==10.2.0)
Requires-Dist: moviepy (==1.0.3)
Requires-Dist: mpmath (==1.3.0)
Requires-Dist: msal (==1.28.0)
Requires-Dist: msal-extensions (==1.1.0)
Requires-Dist: msgpack (==1.0.7)
Requires-Dist: msrest (==0.7.1)
Requires-Dist: msrestazure (==0.6.4)
Requires-Dist: mtranslate (==1.8)
Requires-Dist: multidict (==6.0.5)
Requires-Dist: networkx (==3.2.1)
Requires-Dist: nh3 (==0.2.17)
Requires-Dist: numba (==0.59.0)
Requires-Dist: numpy (==1.26.3)
Requires-Dist: oauthlib (==3.2.2)
Requires-Dist: openai (==0.6.0)
Requires-Dist: openpyxl (==3.1.2)
Requires-Dist: packaging (==23.2)
Requires-Dist: pandas (==2.2.1)
Requires-Dist: pandas-stubs (==2.2.1.240316)
Requires-Dist: pefile (==2023.2.7)
Requires-Dist: pexpect (==4.9.0)
Requires-Dist: pillow (==10.3.0)
Requires-Dist: pip-tools (==7.4.0)
Requires-Dist: pkginfo (==1.10.0)
Requires-Dist: platformdirs (==4.2.0)
Requires-Dist: pooch (==1.8.1)
Requires-Dist: portalocker (==2.8.2)
Requires-Dist: proglog (==0.1.10)
Requires-Dist: proto-plus (==1.23.0)
Requires-Dist: protobuf (==4.25.2)
Requires-Dist: ptyprocess (==0.7.0)
Requires-Dist: pyasn1 (==0.5.1)
Requires-Dist: pyasn1-modules (==0.3.0)
Requires-Dist: pycparser (==2.21)
Requires-Dist: pydantic (==2.6.4)
Requires-Dist: pydantic-core (==2.16.3)
Requires-Dist: pydub (==0.25.1)
Requires-Dist: Pygments (==2.17.2)
Requires-Dist: pyinstaller (==6.5.0)
Requires-Dist: pyinstaller-hooks-contrib (==2024.3)
Requires-Dist: PyJWT (==2.8.0)
Requires-Dist: pyparsing (==3.1.1)
Requires-Dist: pypiwin32 (==223)
Requires-Dist: pyproject-hooks (==1.0.0)
Requires-Dist: python-dateutil (==2.9.0.post0)
Requires-Dist: pytz (==2024.1)
Requires-Dist: pywin32 (==306)
Requires-Dist: pywin32-ctypes (==0.2.2)
Requires-Dist: PyYAML (==6.0.1)
Requires-Dist: readme-renderer (==43.0)
Requires-Dist: regex (==2023.12.25)
Requires-Dist: requests (==2.31.0)
Requires-Dist: requests-oauthlib (==2.0.0)
Requires-Dist: requests-toolbelt (==1.0.0)
Requires-Dist: rfc3986 (==1.5.0)
Requires-Dist: rich (==13.7.1)
Requires-Dist: rsa (==4.9)
Requires-Dist: safetensors (==0.4.2)
Requires-Dist: scikit-learn (==1.4.1.post1)
Requires-Dist: scipy (==1.12.0)
Requires-Dist: sh (==2.0.6)
Requires-Dist: six (==1.16.0)
Requires-Dist: sniffio (==1.3.0)
Requires-Dist: soundfile (==0.12.1)
Requires-Dist: soxr (==0.3.7)
Requires-Dist: supyr-struct (==1.5.4)
Requires-Dist: sympy (==1.12)
Requires-Dist: threadpoolctl (==3.3.0)
Requires-Dist: tokenizers (==0.15.2)
Requires-Dist: toml (==0.10.2)
Requires-Dist: torchaudio (==2.2.2)
Requires-Dist: torchvision (==0.17.2)
Requires-Dist: tqdm (==4.66.1)
Requires-Dist: transformers (==4.39.2)
Requires-Dist: translate (==3.6.1)
Requires-Dist: twine (==5.0.0)
Requires-Dist: types-pytz (==2024.1.0.20240203)
Requires-Dist: typing-extensions (==4.9.0)
Requires-Dist: tzdata (==2024.1)
Requires-Dist: uritemplate (==4.1.1)
Requires-Dist: urllib3 (==2.2.1)
Requires-Dist: uuid (==1.30)
Requires-Dist: virtualenv (==20.25.1)
Requires-Dist: watch (==0.2.7)
Requires-Dist: Werkzeug (==3.0.1)
Requires-Dist: whichcraft (==0.6.1)
Requires-Dist: yarl (==1.9.4)
Requires-Dist: zipp (==3.18.1)
Requires-Dist: zope.event (==5.0)
Requires-Dist: zope.interface (==6.2)
